edflib-0.86.4.dist-info/top_level.txt
edflib-0.86.4.dist-info/RECORD
edflib-0.86.4.dist-info/METADATA
edflib-0.86.4.dist-info/WHEEL
edflib/sandbox.py
edflib/testint16.py
edflib/_edflib.cpython-39-x86_64-linux-gnu.so
edflib/__init__.py
edflib/_edflib.pyx
edflib/edfwriter.py
edflib/edfreader.py
edflib/edf.pxi
edflib/purepythonheader.py
edflib/_edflib.c
edflib/utils/standardtexts.py
