Metadata-Version: 2.1
Name: edflib
Version: 0.86.4
Summary: python edflib is a python package ot allow access to European Data Format files (EDF for short). This is a standard for biological signals such as EEG, evoked potentials and EMG.  This module wraps Teunis van Beelen's edflib. Unless you have good reason to use this package, you may want to use pyedflib instead as it is more actively and better maintained.
Author: Chris Lee-Messer
Requires-Python: >=3.9
Requires-Dist: future
Requires-Dist: numpy>1.22
Provides-Extra: dev
Requires-Dist: pytest; extra == "dev"
Requires-Dist: cython>=3.0; extra == "dev"
Provides-Extra: test
Requires-Dist: pytest; extra == "test"
